{
	"info": {
		"_postman_id": "3fb971d5-b314-424b-a7d5-1da3bc7b6555",
		"name": "ms-student",
		"schema": "https://schema.getpostman.com/json/collection/v2.1.0/collection.json",
		"_exporter_id": "4439064",
		"_collection_link": "https://restless-station-487713.postman.co/workspace/microservice~349d98d5-e67a-4244-a53f-3b021562d3ac/collection/4439064-3fb971d5-b314-424b-a7d5-1da3bc7b6555?action=share&source=collection_link&creator=4439064"
	},
	"item": [
		{
			"name": "Create Student",
			"request": {
				"method": "POST",
				"header": [],
				"body": {
					"mode": "raw",
					"raw": "{\r\n    \"name\" : \"Rasya Aditia\",\r\n    \"age\" : 25,\r\n    \"gender\" : \"Male\",\r\n    \"schoolId\" : 1\r\n}",
					"options": {
						"raw": {
							"language": "json"
						}
					}
				},
				"url": {
					"raw": "http://localhost:9000/student",
					"protocol": "http",
					"host": [
						"localhost"
					],
					"port": "9000",
					"path": [
						"student"
					]
				}
			},
			"response": []
		},
		{
			"name": "Update Student",
			"request": {
				"method": "PUT",
				"header": [],
				"body": {
					"mode": "raw",
					"raw": "{\r\n    \"id\": 1,\r\n    \"name\": \"Rasya Aditia Prawira\",\r\n    \"age\": 25,\r\n    \"gender\": \"Male\",\r\n    \"schoolId\": 1\r\n}",
					"options": {
						"raw": {
							"language": "json"
						}
					}
				},
				"url": {
					"raw": "http://localhost:9000/student",
					"protocol": "http",
					"host": [
						"localhost"
					],
					"port": "9000",
					"path": [
						"student"
					]
				}
			},
			"response": []
		},
		{
			"name": "Get Student",
			"request": {
				"method": "GET",
				"header": [],
				"url": {
					"raw": "http://localhost:9000/student",
					"protocol": "http",
					"host": [
						"localhost"
					],
					"port": "9000",
					"path": [
						"student"
					]
				}
			},
			"response": []
		},
		{
			"name": "Get Student By ID",
			"request": {
				"method": "GET",
				"header": [],
				"url": {
					"raw": "http://localhost:9000/student/1",
					"protocol": "http",
					"host": [
						"localhost"
					],
					"port": "9000",
					"path": [
						"student",
						"1"
					]
				}
			},
			"response": []
		},
		{
			"name": "Delete Student",
			"request": {
				"method": "DELETE",
				"header": [],
				"url": {
					"raw": "http://localhost:9000/student/1",
					"protocol": "http",
					"host": [
						"localhost"
					],
					"port": "9000",
					"path": [
						"student",
						"1"
					]
				}
			},
			"response": []
		}
	]
}